omnistore/__init__.py
omnistore/objstore/__init__.py
omnistore/objstore/aliyun_oss.py
omnistore/objstore/objstore.py
omnistore/objstore/objstore_factory.py
omnistore/store.py
omnistore-0.0.4.dist-info/LICENSE
omnistore-0.0.4.dist-info/METADATA
omnistore-0.0.4.dist-info/WHEEL
omnistore-0.0.4.dist-info/RECORD
